dive_jupyterlite_xeus_python/__init__.py
dive_jupyterlite_xeus_python/_version.py
dive_jupyterlite_xeus_python/env_build_addon.py
dive_jupyterlite_xeus_python-0.5.7.data/data/share/jupyter/labextensions/@jupyterlite/xeus-python-kernel/install.json
dive_jupyterlite_xeus_python-0.5.7.data/data/share/jupyter/labextensions/@jupyterlite/xeus-python-kernel/package.json
dive_jupyterlite_xeus_python-0.5.7.data/data/share/jupyter/labextensions/@jupyterlite/xeus-python-kernel/static/112.cb521cc5d56d6fdc8eb7.js
dive_jupyterlite_xeus_python-0.5.7.data/data/share/jupyter/labextensions/@jupyterlite/xeus-python-kernel/static/170.1922c23c2e205f41c70e.js
dive_jupyterlite_xeus_python-0.5.7.data/data/share/jupyter/labextensions/@jupyterlite/xeus-python-kernel/static/213.9a14124442b83113dcbf.js
dive_jupyterlite_xeus_python-0.5.7.data/data/share/jupyter/labextensions/@jupyterlite/xeus-python-kernel/static/5c9063b436cedf0567480fe487ece0d1479ea9545f310cba93fa184ccbab290d.png
dive_jupyterlite_xeus_python-0.5.7.data/data/share/jupyter/labextensions/@jupyterlite/xeus-python-kernel/static/747.db1b011ede666813d89f.js
dive_jupyterlite_xeus_python-0.5.7.data/data/share/jupyter/labextensions/@jupyterlite/xeus-python-kernel/static/870.4cd7d76b7a2d9ae4668e.js
dive_jupyterlite_xeus_python-0.5.7.data/data/share/jupyter/labextensions/@jupyterlite/xeus-python-kernel/static/e32b5c282072d717887b60da73178fdd35a65dc3caeacba7a026e5a4255cc997.png
dive_jupyterlite_xeus_python-0.5.7.data/data/share/jupyter/labextensions/@jupyterlite/xeus-python-kernel/static/python_data.data
dive_jupyterlite_xeus_python-0.5.7.data/data/share/jupyter/labextensions/@jupyterlite/xeus-python-kernel/static/python_data.js
dive_jupyterlite_xeus_python-0.5.7.data/data/share/jupyter/labextensions/@jupyterlite/xeus-python-kernel/static/remoteEntry.05c0309d9730051bf75d.js
dive_jupyterlite_xeus_python-0.5.7.data/data/share/jupyter/labextensions/@jupyterlite/xeus-python-kernel/static/style.js
dive_jupyterlite_xeus_python-0.5.7.dist-info/LICENSE
dive_jupyterlite_xeus_python-0.5.7.dist-info/METADATA
dive_jupyterlite_xeus_python-0.5.7.dist-info/WHEEL
dive_jupyterlite_xeus_python-0.5.7.dist-info/entry_points.txt
dive_jupyterlite_xeus_python-0.5.7.dist-info/top_level.txt
dive_jupyterlite_xeus_python-0.5.7.dist-info/RECORD
