Metadata-Version: 2.1
Name: dive-jupyterlite-xeus-python
Version: 0.5.7
Summary: A Python kernel for JupyterLite, powered by Xeus
Home-page: https://github.com/jupyterlite/xeus-python-kernel
Author: Thorsten Beier, JupyterLite Contributors
Author-email: 
License: BSD-3-Clause
Keywords: Jupyter,JupyterLab,JupyterLab3
Platform: Linux
Platform: Mac OS X
Platform: Windows
Classifier: License :: OSI Approved :: BSD License
Classifier: Programming Language :: Python
Classifier: Programming Language :: Python :: 3
Classifier: Programming Language :: Python :: 3.6
Classifier: Programming Language :: Python :: 3.7
Classifier: Programming Language :: Python :: 3.8
Classifier: Programming Language :: Python :: 3.9
Classifier: Programming Language :: Python :: 3.10
Classifier: Framework :: Jupyter
Classifier: Framework :: Jupyter :: JupyterLab
Classifier: Framework :: Jupyter :: JupyterLab :: 3
Classifier: Framework :: Jupyter :: JupyterLab :: Extensions
Classifier: Framework :: Jupyter :: JupyterLab :: Extensions :: Prebuilt
Requires-Python: >=3.6
License-File: LICENSE
Requires-Dist: traitlets
Requires-Dist: jupyterlite
Requires-Dist: requests
Requires-Dist: empack (<2,>=1.0.0)
